README
fb.py
setup.py
fb.py.egg-info/PKG-INFO
fb.py.egg-info/SOURCES.txt
fb.py.egg-info/dependency_links.txt
fb.py.egg-info/entry_points.txt
fb.py.egg-info/not-zip-safe
fb.py.egg-info/requires.txt
fb.py.egg-info/top_level.txt