Metadata-Version: 1.0
Name: fb.py
Version: 0.1
Summary: Python binding to Facebook Graph API
Home-page: UNKNOWN
Author: Andrey Popp
Author-email: 8mayday@gmail.com
License: BSD
Platform: UNKNOWN
